CancerDockPredict/5gs4.pdbqt
CancerDockPredict/CancerDockPredict.py
CancerDockPredict/__init__.py
CancerDockPredict/padel_model.joblib
CancerDockPredict-0.0.1.dist-info/LICENSE
CancerDockPredict-0.0.1.dist-info/METADATA
CancerDockPredict-0.0.1.dist-info/WHEEL
CancerDockPredict-0.0.1.dist-info/top_level.txt
CancerDockPredict-0.0.1.dist-info/RECORD
