Metadata-Version: 2.1
Name: CancerDockPredict
Version: 0.0.1
Summary: Python package that calculates Lipinsky descriptors, predicts pIC50 and performs docking
Home-page: https://github.com/clabe-wekesa/CancerDockPredict
Author: Edwin Mwakio, Clabe Wekesa, Patrick okoth
Author-email: simiyu86wekesa@gmail.com
License: MIT
Classifier: License :: OSI Approved :: MIT License
Classifier: Programming Language :: Python :: 3
Classifier: Programming Language :: Python :: 3.6
Classifier: Programming Language :: Python :: 3.7
Classifier: Programming Language :: Python :: 3.8
Classifier: Programming Language :: Python :: 3.9
Classifier: Programming Language :: Python :: 3.10
Classifier: Programming Language :: Python :: 3.11
Classifier: Operating System :: OS Independent
License-File: LICENSE
Requires-Dist: rdkit
Requires-Dist: pandas
Requires-Dist: padelpy
Requires-Dist: joblib
Requires-Dist: meeko
Requires-Dist: scikit-learn
Requires-Dist: scipy
Requires-Dist: numpy
